{
  "title": "English",
  "prices": [
    {
      "tier": "FREE",
      "text": "For transport companies with up till 10 stops*",
      "price": "free of charge",
      "subtext": "0.- €/year"
    },
    {
      "tier": "MINI",
      "text": "For transport companies with **11-200** stops or **1-10** railway stations*",
      "price": "2'700.–",
      "subtext": "2'700 €/year"
    },
    {
      "tier": "MIDI",
      "text": "For transport companies with **201-500** stops or **11-100** railway stations*",
      "price": "5'900.–",
      "subtext": "5'900 €/year"
    },
    {
      "tier": "MAXI",
      "text": "For transport companies with more than **501** stops or **101-200** railway stations*",
      "price": "8'400.–",
      "subtext": "8'400 C€HF/year"
    }
  ]
}